{
  "type": "excalidraw",
  "version": 2,
  "source": "https://excalidraw.com",
  "elements": [
    {
      "type": "text",
      "version": 1,
      "versionNonce": 193698,
      "isDeleted": false,
      "id": "text-459013",
      "fillStyle": "solid",
      "strokeWidth": 1,
      "strokeStyle": "solid",
      "roughness": 0,
      "opacity": 100,
      "angle": 0,
      "x": 100,
      "y": 50,
      "strokeColor": "#0f172a",
      "backgroundColor": "transparent",
      "width": 800,
      "height": 36.4,
      "seed": 1001,
      "groupIds": [],
      "frameId": null,
      "roundness": null,
      "boundElements": [],
      "updated": 1600000000,
      "text": "Key Innovations & Engineering Decisions",
      "fontSize": 28,
      "fontFamily": 2,
      "textAlign": "center",
      "verticalAlign": "top",
      "containerId": null,
      "originalText": "Key Innovations & Engineering Decisions",
      "lineHeight": 1.25
    },
    {
      "type": "rectangle",
      "version": 1,
      "versionNonce": 206112,
      "isDeleted": false,
      "id": "rect-181263",
      "fillStyle": "solid",
      "strokeWidth": 2,
      "strokeStyle": "solid",
      "roughness": 0,
      "opacity": 100,
      "angle": 0,
      "x": 80,
      "y": 130,
      "strokeColor": "#3b82f6",
      "backgroundColor": "#eff6ff",
      "width": 400,
      "height": 130,
      "seed": 1002,
      "groupIds": [],
      "frameId": null,
      "roundness": {
        "type": 3
      },
      "boundElements": [],
      "updated": 1600000000
    },
    {
      "type": "text",
      "version": 1,
      "versionNonce": 330964,
      "isDeleted": false,
      "id": "text-900237",
      "fillStyle": "solid",
      "strokeWidth": 1,
      "strokeStyle": "solid",
      "roughness": 0,
      "opacity": 100,
      "angle": 0,
      "x": 95,
      "y": 145,
      "strokeColor": "#0f172a",
      "backgroundColor": "transparent",
      "width": 370,
      "height": 23.400000000000002,
      "seed": 1003,
      "groupIds": [],
      "frameId": null,
      "roundness": null,
      "boundElements": [],
      "updated": 1600000000,
      "text": "Behavioral & Statistical Trust Signals",
      "fontSize": 18,
      "fontFamily": 2,
      "textAlign": "center",
      "verticalAlign": "top",
      "containerId": null,
      "originalText": "Behavioral & Statistical Trust Signals",
      "lineHeight": 1.25
    },
    {
      "type": "text",
      "version": 1,
      "versionNonce": 182998,
      "isDeleted": false,
      "id": "text-442522",
      "fillStyle": "solid",
      "strokeWidth": 1,
      "strokeStyle": "solid",
      "roughness": 0,
      "opacity": 100,
      "angle": 0,
      "x": 95,
      "y": 185,
      "strokeColor": "#0f172a",
      "backgroundColor": "transparent",
      "width": 370,
      "height": 16.900000000000002,
      "seed": 1004,
      "groupIds": [],
      "frameId": null,
      "roundness": null,
      "boundElements": [],
      "updated": 1600000000,
      "text": "Avoids uncalibrated self-confidence. Uses code compilation, logprob token entropy, and cosine similarity over alternative outputs.",
      "fontSize": 13,
      "fontFamily": 2,
      "textAlign": "left",
      "verticalAlign": "top",
      "containerId": null,
      "originalText": "Avoids uncalibrated self-confidence. Uses code compilation, logprob token entropy, and cosine similarity over alternative outputs.",
      "lineHeight": 1.25
    },
    {
      "type": "rectangle",
      "version": 1,
      "versionNonce": 737815,
      "isDeleted": false,
      "id": "rect-597112",
      "fillStyle": "solid",
      "strokeWidth": 2,
      "strokeStyle": "solid",
      "roughness": 0,
      "opacity": 100,
      "angle": 0,
      "x": 520,
      "y": 130,
      "strokeColor": "#10b981",
      "backgroundColor": "#ecfdf5",
      "width": 400,
      "height": 130,
      "seed": 1005,
      "groupIds": [],
      "frameId": null,
      "roundness": {
        "type": 3
      },
      "boundElements": [],
      "updated": 1600000000
    },
    {
      "type": "text",
      "version": 1,
      "versionNonce": 667464,
      "isDeleted": false,
      "id": "text-593540",
      "fillStyle": "solid",
      "strokeWidth": 1,
      "strokeStyle": "solid",
      "roughness": 0,
      "opacity": 100,
      "angle": 0,
      "x": 535,
      "y": 145,
      "strokeColor": "#0f172a",
      "backgroundColor": "transparent",
      "width": 370,
      "height": 23.400000000000002,
      "seed": 1006,
      "groupIds": [],
      "frameId": null,
      "roundness": null,
      "boundElements": [],
      "updated": 1600000000,
      "text": "Local Embedding Self-Consistency",
      "fontSize": 18,
      "fontFamily": 2,
      "textAlign": "center",
      "verticalAlign": "top",
      "containerId": null,
      "originalText": "Local Embedding Self-Consistency",
      "lineHeight": 1.25
    },
    {
      "type": "text",
      "version": 1,
      "versionNonce": 183115,
      "isDeleted": false,
      "id": "text-180567",
      "fillStyle": "solid",
      "strokeWidth": 1,
      "strokeStyle": "solid",
      "roughness": 0,
      "opacity": 100,
      "angle": 0,
      "x": 535,
      "y": 185,
      "strokeColor": "#0f172a",
      "backgroundColor": "transparent",
      "width": 370,
      "height": 16.900000000000002,
      "seed": 1007,
      "groupIds": [],
      "frameId": null,
      "roundness": null,
      "boundElements": [],
      "updated": 1600000000,
      "text": "Generates alternative responses at temperature=0.7 and checks semantic convergence using local vector embeddings.",
      "fontSize": 13,
      "fontFamily": 2,
      "textAlign": "left",
      "verticalAlign": "top",
      "containerId": null,
      "originalText": "Generates alternative responses at temperature=0.7 and checks semantic convergence using local vector embeddings.",
      "lineHeight": 1.25
    },
    {
      "type": "rectangle",
      "version": 1,
      "versionNonce": 416651,
      "isDeleted": false,
      "id": "rect-801830",
      "fillStyle": "solid",
      "strokeWidth": 2,
      "strokeStyle": "solid",
      "roughness": 0,
      "opacity": 100,
      "angle": 0,
      "x": 80,
      "y": 290,
      "strokeColor": "#f97316",
      "backgroundColor": "#fff7ed",
      "width": 400,
      "height": 130,
      "seed": 1008,
      "groupIds": [],
      "frameId": null,
      "roundness": {
        "type": 3
      },
      "boundElements": [],
      "updated": 1600000000
    },
    {
      "type": "text",
      "version": 1,
      "versionNonce": 466195,
      "isDeleted": false,
      "id": "text-994117",
      "fillStyle": "solid",
      "strokeWidth": 1,
      "strokeStyle": "solid",
      "roughness": 0,
      "opacity": 100,
      "angle": 0,
      "x": 95,
      "y": 305,
      "strokeColor": "#0f172a",
      "backgroundColor": "transparent",
      "width": 370,
      "height": 23.400000000000002,
      "seed": 1009,
      "groupIds": [],
      "frameId": null,
      "roundness": null,
      "boundElements": [],
      "updated": 1600000000,
      "text": "Dynamic Budget Telemetry & Adjustments",
      "fontSize": 18,
      "fontFamily": 2,
      "textAlign": "center",
      "verticalAlign": "top",
      "containerId": null,
      "originalText": "Dynamic Budget Telemetry & Adjustments",
      "lineHeight": 1.25
    },
    {
      "type": "text",
      "version": 1,
      "versionNonce": 250109,
      "isDeleted": false,
      "id": "text-803169",
      "fillStyle": "solid",
      "strokeWidth": 1,
      "strokeStyle": "solid",
      "roughness": 0,
      "opacity": 100,
      "angle": 0,
      "x": 95,
      "y": 345,
      "strokeColor": "#0f172a",
      "backgroundColor": "transparent",
      "width": 370,
      "height": 16.900000000000002,
      "seed": 1010,
      "groupIds": [],
      "frameId": null,
      "roundness": null,
      "boundElements": [],
      "updated": 1600000000,
      "text": "Monitors actual-to-target token burn ratios. Tightens/relaxes thresholds to guarantee staying above accuracy floor.",
      "fontSize": 13,
      "fontFamily": 2,
      "textAlign": "left",
      "verticalAlign": "top",
      "containerId": null,
      "originalText": "Monitors actual-to-target token burn ratios. Tightens/relaxes thresholds to guarantee staying above accuracy floor.",
      "lineHeight": 1.25
    },
    {
      "type": "rectangle",
      "version": 1,
      "versionNonce": 732820,
      "isDeleted": false,
      "id": "rect-515988",
      "fillStyle": "solid",
      "strokeWidth": 2,
      "strokeStyle": "solid",
      "roughness": 0,
      "opacity": 100,
      "angle": 0,
      "x": 520,
      "y": 290,
      "strokeColor": "#0f172a",
      "backgroundColor": "#e2e8f0",
      "width": 400,
      "height": 130,
      "seed": 1011,
      "groupIds": [],
      "frameId": null,
      "roundness": {
        "type": 3
      },
      "boundElements": [],
      "updated": 1600000000
    },
    {
      "type": "text",
      "version": 1,
      "versionNonce": 730774,
      "isDeleted": false,
      "id": "text-218332",
      "fillStyle": "solid",
      "strokeWidth": 1,
      "strokeStyle": "solid",
      "roughness": 0,
      "opacity": 100,
      "angle": 0,
      "x": 535,
      "y": 305,
      "strokeColor": "#0f172a",
      "backgroundColor": "transparent",
      "width": 370,
      "height": 23.400000000000002,
      "seed": 1012,
      "groupIds": [],
      "frameId": null,
      "roundness": null,
      "boundElements": [],
      "updated": 1600000000,
      "text": "Predictive Routing Gate Heuristics",
      "fontSize": 18,
      "fontFamily": 2,
      "textAlign": "center",
      "verticalAlign": "top",
      "containerId": null,
      "originalText": "Predictive Routing Gate Heuristics",
      "lineHeight": 1.25
    },
    {
      "type": "text",
      "version": 1,
      "versionNonce": 884082,
      "isDeleted": false,
      "id": "text-123000",
      "fillStyle": "solid",
      "strokeWidth": 1,
      "strokeStyle": "solid",
      "roughness": 0,
      "opacity": 100,
      "angle": 0,
      "x": 535,
      "y": 345,
      "strokeColor": "#0f172a",
      "backgroundColor": "transparent",
      "width": 370,
      "height": 16.900000000000002,
      "seed": 1013,
      "groupIds": [],
      "frameId": null,
      "roundness": null,
      "boundElements": [],
      "updated": 1600000000,
      "text": "Prevents wasting local tokens. Detects complex domain keywords (integral, calculus, concurrency) to route directly to remote.",
      "fontSize": 13,
      "fontFamily": 2,
      "textAlign": "left",
      "verticalAlign": "top",
      "containerId": null,
      "originalText": "Prevents wasting local tokens. Detects complex domain keywords (integral, calculus, concurrency) to route directly to remote.",
      "lineHeight": 1.25
    }
  ],
  "appState": {
    "viewBackgroundColor": "#ffffff",
    "gridSize": null,
    "zenModeEnabled": false,
    "viewModeEnabled": false
  },
  "files": {}
}